{
	"SwitchPanelAbilities": "",
	"СomboClone": "Clonar Сombo",
	"ShieldMenuDistance": "Distancia",
	"DangerRange": "Danger Range",
	"OrbwalkUnitsModes": "Caminata (Hit & Run)",
	"AbilitiesLotusOrb": "Lotus",
	"COMBO_LINKENS_BREAK": "Esfera de Linken",
	"AbilitiesLinkenSphere": "Esfera de Linken",
	"TRANSLATE_KEY_ESCAPE_TOOLTIP": "En caso de que te ataquen y necesites\npara reaccionar rápidamente, usa este modo.\nEl héroe utiliza los objetos y habilidades seleccionados\nen el enemigo o si es un parpadeo o\nuna facultad similar será usada en la dirección de tu cursor",
	"Mode": "Modo",
	"Lanes": "Lanes",
	"FARM": "FARMA",
	"Lane": "Senda",
	"Jungle": "Jungla",
	"Await": "Esperar",
	"Key": "Clave",
	"Reset": "Reset",
	"Color 1": "Color 1",
	"Color 2": "Color 2",
	"Strength": "Intensidad",
	"Size": "Tamaño",
	"Combo": "Combo",
	"Escape": "Escape",
	"Mini": "Mini",
	"Center": "Centrar",
	"Modes": "Modos",
	"Dynamic": "Dinámica",
	"State": "Estado",
	"Count": "Contador",
	"Hook ally": "Hook aliado",
	"Items": "Elementos",
	"Move": "Mover",
	"For the": "Para el",
	"disabled": "deshabilitado",
	"Attack": "Ataque",
	"Settings": "Ajustes",
	"Abilities": "Habilidades",
	"Invisibility": "Invisibilidad",
	"Use": "Usar",
	"On target": "En objetivo",
	"On self": "Sí mismo",
	"Units": "Unidades",
	"in combo": "en combo",
	"Orbwalk": "Orbera",
	"(clone)": "(clonar)",
	"(illusion)": "(ilusión)",
	"Body block": "Bloque corporal",
	"Kill steal": "Robar muertes",
	"Damage Bar": "Barra de daño",
	"Position: X": "Posición: X",
	"Position: Y": "Posición: Y",
	"Agility": "Agilidad",
	"Allways": "Allways",
	"Intellect": "Intelecto",
	"Controlled": "Controlado",
	"Draw target": "Dibujar objetivo",
	"Delay (ms)": "Retraso (ms)",
	"Heroes disabled": "Héroes desactivados",
	"Input block": "Bloque de entrada",
	"Controlled heroes": "Héroes controlados",
	"Draw target particle": "Dibujar la partícula objetivo",
	"Auto": "Auto",
	"Custom": "Personalizado",
	"LBM": "LBM",
	"Switch panel": "Cambiar panel",
	"Left center": "Centro izquierdo",
	"Right center": "Centro derecho",
	"Top center": "Centro superior",
	"Top left": "Arriba izquierda",
	"Top right": "Arriba derecha",
	"Bot center": "Centro de bot",
	"Bot left": "Botín restante",
	"Bot right": "Botín derecho",
	"Use ability": "Usar habilidad",
	"Min. Distance": "Distancia mínima",
	"If target in ghost": "Si el objetivo en fantasma",
	"Enemy count": "Conteo enemigo",
	"Auto farm/push": "Autogranja/empuje",
	"General settings": "Ajustes generales",
	"Alternative combo": "Combinación alternativa",
	"Combo not supported": "Combo no soportado",
	"Ancient camp": "Campamento antiguo",
	"Enemy jungle": "Selva enemiga",
	"HP threshold %": "Umbral de HP %",
	"Lock target": "Bloquear destino",
	"Target selector": "Target selector",
	"Focus target": "Destino de enfoque",
	"Near mouse": "Ratón cercano",
	"Near hero": "Héroe cercano",
	"Death switch": "Interruptor de muerte",
	"Lowest health": "La salud más baja",
	"Raze direction": "Dirección del carro",
	"X-mark + TP Base": "X-mark + TP Base",
	"Harass (Tidebringer)": "Harass (Tidebringer)",
	"Illusions on lane": "Illusiones en la vía",
	"Illusions on one camp": "Illusiones en un campamento",
	"Delay click move (ms)": "Retrasar movimiento de clic (ms)",
	"Fail safe": "Fallo seguro",
	"Pause on combo": "Pausar en combo",
	"Harass (Psi Blades)": "Abuso (espadas si)",
	"Is visible for enemies": "Es visible para enemigos",
	"Need enemy hero": "Necesita héroe enemigo",
	"Ignore blade mail": "Ignorar correo de hoja",
	"Ignore invisibility": "Ignorar invisibilidad",
	"Stunned/rooted only": "Solo aturdido/rooteado",
	"Orbwalk mode": "Modo Orbwalk",
	"Move to target": "Mover al objetivo",
	"Move to mouse": "Mover al ratón",
	"Additional delay": "Retraso adicional",
	"Stop orbwalk if standing": "Parar la orbla si está de pie",
	"Danger move to mouse": "Mover peligro al ratón",
	"Enable distance from enemy": "Habilita la distancia del enemigo",
	"Distance from enemy": "Distancia del enemigo",
	"Min distance from mouse": "Distancia mínima del ratón",
	"Min distance for use": "Distancia mínima para uso",
	"Safe 1 charge": "Cargo seguro 1",
	"Min distance for target": "Distancia mínima para el objetivo",
	"Move to shackle": "Mover al grillete",
	"Additional targets": "Objetivos adicionales",
	"Binds for turn off/on": "Enlaces para apagar/encender",
	"Lock target while combo is active": "Bloquear objetivo mientras la combinación está activa",
	"Text position 'ON/OFF' on items": "Posición del texto 'ON/OFF' en los elementos",
	"Text position 'ON/OFF' on abilities": "Posición del texto 'ON/OFF' en habilidades",
	"Panel for fast turn on/off abilities/items": "Panel para activación/desactivación rápida",
	"- Mini: Drawing a separate panel\n- Dynamic: on abilities/items selected on unit": "- Mini: Dibujar un panel separado\n- Dinámico: en habilidades/objetos seleccionados en la unidad",
	"Panel for fast turn on/off abilities/items\nEnable abilities and items in game": "Panel para activar/desactivar habilidades/objetos rápidamente\nHabilita habilidades y objetos en el juego",
	"Auto switch target if previous died": "Cambio automático de destino si ha muerto anterior",
	"Allow to target units like\nspirit bear: wards: courier: tombstone etc.": "Permite asignar unidades como el oso de espíritu de\n: wards: courier: tumbstone etc.",
	"Auto position your hero\nto shackle the enemy": "Posición automática de tu héroe\npara atrapar al enemigo",
	"Use only if target is disabled": "Usar sólo si el objetivo está desactivado",
	"Min distance from you\nto the target for usage": "Distancia mínima de ti\nal objetivo para uso",
	"Use ability only when enemy is moving in the same direction": "Usa la habilidad sólo cuando el enemigo se mueve en la misma dirección",
	"Auto use XReturn - torrent ghostship": "Uso automático XReturn - nave fantasma torrent",
	"Hit'n'run - attack and move": "Golpear - atacar y mover",
	"Unit will not move closer to the target": "La unidad no se acercará al objetivo",
	"Unit will not orbwalk\nif target is standing": "La unidad no podrá caminar\nsi el objetivo está de pie",
	"Unit(s) will try to body block the target in combo modes": "Unidad(es) intentará bloquear al objetivo en modos combinados",
	"Set additional delay\nif unit cancels auto attack": "Establecer retraso adicional\nsi la unidad cancela el autoataque",
	"Allows the unit to use items\nin combo modes": "Permite a la unidad usar objetos\nen modos combo",
	"Allows the unit to use abilities\nin combo modes": "Permite a la unidad usar habilidades\nen modos combo",
	"Unit will move to mouse without\nattacking when in danger range": "La unidad se moverá al ratón sin\nataques cuando esté en rango de peligro",
	"Module controllable units at combo modes\nThere can be both the main character\nand the illusions of your hero\nand his controllable units": "Unidades controlables de módulos en modos combinados\nPuede haber tanto el personaje principal\ncomo las ilusiones de tu héroe\ny sus unidades controlables",
	"Use ability only when\nenemy is stunned/rooted": "Usar habilidad solo cuando\nenemigo está aturdido/enraizado",
	"Cancel ability\nif it won't hit the target\nworked for kill steal & combo mode": "Cancela la habilidad\nsi no alcanza el objetivo\ntrabajado para robar muertes y modo combo",
	"Allows the unit to use items\nin auto farm": "Permite a la unidad usar artículos\nen la granja automática",
	"Allows the unit to use abilities\nin auto farm": "Permite a la unidad usar habilidades\nen la granja automática",
	"Delay between move units (recomended 777-1500)": "Retraso entre unidades de movimiento (recomendado 777-1500)",
	"Control disconnected heroes": "Control de héroes desconectados",
	"Requires controlled/disconnected heroes": "Requiere héroes controlados/desconectados",
	"Color activated combo mode": "Modo combinado de color activado",
	"Color deactivated combo mode": "Modo combinado de color desactivado",
	"Control ally hero if disconnected": "Controla el héroe aliado si se desconecta",
	"Block input in dota when using\nbinds in combo modes or harass\nuseful if your bind is the same as ability and item in dota\nbut it can get in the way if you use 2-x units for example\ncombo on Lone druid": "Bloquear la entrada en dota al usar\nataduras en modos combinados o acosar\nútil si tu enlace es lo mismo que la habilidad y el objeto en dota\npero puede interponerse si usas 2 unidades x por ejemplo\ncombo en druida solitaria",
	"Please: create lobby for kill steal": "Por favor: crear lobby para robar muertes",
	"Pause kill stealer when combo is active": "Pausar el robo de muertes cuando la combinación está activa",
	"If hero not selected kill steal for hero disabled": "Si el héroe no seleccionado roba muertes por héroe desactivado",
	"Use abilities/items\nhas active blade mail": "Usar habilidades/artículos\ntiene correo activo",
	"Use abilities/items\nwhen hero is invisible for enemies": "Usa habilidades/objetos\ncuando el héroe es invisible para los enemigos",
	"Use abilities when hero is invisible": "Usar habilidades cuando el héroe es invisible",
	"Used in linken sphere. To set priority\nhold CTRL and move one image to another": "Utilizado en la esfera vinculada. Para establecer prioridad\nmantén pulsado CTRL y mueve una imagen a otra",
	"Used in lotus orb. To set priority\nhold CTRL and move one image to another": "Utilizado en el orb. Para establecer prioridad\nmantén pulsado CTRL y mueve una imagen a otra",
	"Use abilities when the hero\nis invisible but you are visible": "Usa habilidades cuando el héroe\nes invisible pero tú eres visible",
	"to work required\nEnable (settings -> humanizer)\nDisable (settings -> obs bypass)": "para trabajar requerido\nActivar (ajustes -> humanizador)\nDesactivar (ajustes -> obs bypass)",
	"Allways - Always used when an enemy is in range\nAuto - Used when an enemy is in range and is using an ability.": "Siempre - Siempre usado cuando un enemigo está en el rango\nAuto - Utilizado cuando un enemigo está en el rango y está usando una habilidad."
}
