{
	"ItemPanel_KeyMode": "Режим бінда",
	"ItemPanel_Key": "Бінд",
	"ItemPanel_Keys": "Бінди",
	"ItemPanel_EmptySlot": "Показати порожні слоти",
	"ItemPanel_Charge_State": "Показати заряди",
	"ItemPanel_Cooldwn_State": "Показати перезарядження",
	"ItemPanel_PingClick2": "Надіслати запит по кліку",
	"ItemPanel_Drag": "< Перетягніть >",
	"Ally": "Союзник",
	"Item Panel": "Панель предметів",
	"Backpack": "Рюкзак",
	"Hold key": "Утримувати",
	"Toggled": "Перемикати",
	"Key bind turn on/off panel": "Клавіші бінда увімк./вимк. панель",
	"Hide items": "Приховати предмети",
	"Couriers": "Кур'єри",
	"Cooldown format time": "Формат часу перезаряджання",
	"Show cooldown format time (min:sec)": "Показати час у форматі (хв:сек)"
}
