{
	"State": "State",
	"Color": "Color",
	"Size": "Size",
	"Distance": "Distance",
	"Draw type": "Draw type",
	"Circle": "Circle",
	"Images": "Images",
	"Reset": "Reset",
	"Hide illusions": "Hide illusions",
	"Settings": "Settings",
	"Show Illusions": "Show Illusions",
	"Setting up invisible illusions": "Setting up invisible illusions",
	"Clones": "Clones",
	"Illusion": "Illusion",
	"Clones color (e.x Meepo, Vengeful spirit)": "Clones color (e.x Meepo, Vengeful spirit)",
	"The distance from you to the illusion\nat which the illusion becomes invisible": "The distance from you to the illusion\nat which the illusion becomes invisible"
}
